netrandom/__init__.py
netrandom/rand_ip.py
netrandom/rand_mac.py
netrandom-0.2.0.dist-info/LICENSE
netrandom-0.2.0.dist-info/METADATA
netrandom-0.2.0.dist-info/WHEEL
netrandom-0.2.0.dist-info/RECORD
