Metadata-Version: 2.1
Name: netrandom
Version: 0.2.0
Summary: Generate random network addresses
License: Apache-2.0
Author: Patrick Keohane
Author-email: pgkeohane@gmail.com
Requires-Python: >=3.7,<4.0
Classifier: License :: OSI Approved :: Apache Software License
Classifier: Programming Language :: Python :: 3
Classifier: Programming Language :: Python :: 3.7
Classifier: Programming Language :: Python :: 3.8
Classifier: Programming Language :: Python :: 3.9
Classifier: Programming Language :: Python :: 3.10
Classifier: Programming Language :: Python :: 3.11
